maticalgos/__init__.py
maticalgos/sparkLib/__init__.py
maticalgos/sparkLib/order_websocket.py
maticalgos/sparkLib/sparkLib.py
maticalgos/sparkLib/utility/__init__.py
maticalgos/sparkLib/utility/dataws/__init__.py
maticalgos/sparkLib/utility/dataws/angelws.py
maticalgos/sparkLib/utility/dataws/fyersws.py
maticalgos/sparkLib/utility/dataws/iiflxtsws.py
maticalgos/sparkLib/utility/dataws/kotakws.py
maticalgos/sparkLib/utility/dataws/shoonyaws.py
maticalgos/sparkLib/utility/dataws/upstoxWS.py
maticalgos/sparkLib/utility/dataws/dependencies/MarketDataFeedUps.py
maticalgos/sparkLib/utility/dataws/dependencies/UpstoxDataws.py
maticalgos/sparkLib/utility/dataws/dependencies/XTSdataApi.py
maticalgos/sparkLib/utility/dataws/dependencies/XTSdataSocket.py
maticalgos/sparkLib/utility/dataws/dependencies/__init__.py
maticalgos/sparkLib/utility/dataws/dependencies/kotakData.py
maticalgos/sparkLib/utility/dataws/dependencies/kotakDataBase.py
maticalgos/sparkLib/utility/dataws/dependencies/shoonyaDataWS.py
maticalgos/sparkLib/utility/dataws/dependencies/smartDataWS.py
maticalgos/sparkLib/utility/dataws/dependencies/fyersAPIv3/__init__.py
maticalgos/sparkLib/utility/dataws/dependencies/fyersAPIv3/data_ws.py
maticalgos/sparkLib/utility/dataws/dependencies/fyersAPIv3/defines.py
maticalgos/sparkLib/utility/dataws/dependencies/fyersAPIv3/fyers_logger.py
maticalgos/sparkLib/utility/dataws/dependencies/fyersAPIv3/map.json
maticalgos/sparkLib/utility/historicalAPI/__init__.py
maticalgos/sparkLib/utility/historicalAPI/historicalData.py
maticalgos/sparkLib/utility/historicalAPI/historicalForTrading.py
maticalgos/sparkLib/utility/historicalAPI/dependencies/IiflHist.py
maticalgos/sparkLib/utility/historicalAPI/dependencies/ShoonyaHist.py
maticalgos/sparkLib/utility/historicalAPI/dependencies/__init__.py
maticalgos/sparkLib/utility/historicalAPI/dependencies/angelHist.py
maticalgos/sparkLib/utility/historicalAPI/dependencies/fyersHist.py
maticalgos_spark-0.2.4.dist-info/METADATA
maticalgos_spark-0.2.4.dist-info/WHEEL
maticalgos_spark-0.2.4.dist-info/top_level.txt
maticalgos_spark-0.2.4.dist-info/RECORD
