Metadata-Version: 2.1
Name: maticalgos-spark
Version: 0.2.4
Summary: SparkLib is a Python client library for interacting with https://spark.maticalgos.com . It provides functionalities to manage accounts, strategies, place orders, and much more.
Author: Niraj Munot
Author-email: nirajmunot28@gmail.com
Classifier: Programming Language :: Python :: 3
Classifier: License :: OSI Approved :: MIT License
Classifier: Operating System :: OS Independent
Requires-Python: >=3.6
Requires-Dist: websocket-client (==1.7.0)
Requires-Dist: numpy (==1.26.4)
Requires-Dist: requests (==2.31.0)
Provides-Extra: dataws
Requires-Dist: python-engineio (==3.13.0) ; extra == 'dataws'
Requires-Dist: python-socketio (==4.6.0) ; extra == 'dataws'
Requires-Dist: aws-lambda-powertools (==1.25.5) ; extra == 'dataws'
Requires-Dist: websockets (==13.0.1) ; extra == 'dataws'
Requires-Dist: protobuf (==5.28.1) ; extra == 'dataws'
Provides-Extra: full
Requires-Dist: python-engineio (==3.13.0) ; extra == 'full'
Requires-Dist: python-socketio (==4.6.0) ; extra == 'full'
Requires-Dist: aws-lambda-powertools (==1.25.5) ; extra == 'full'
Requires-Dist: websockets (==13.0.1) ; extra == 'full'
Requires-Dist: protobuf (==5.28.1) ; extra == 'full'
Requires-Dist: websocket-client (==1.7.0) ; extra == 'full'
Requires-Dist: numpy (==1.26.4) ; extra == 'full'
Requires-Dist: requests (==2.31.0) ; extra == 'full'
Requires-Dist: pyzmq (==26.2.0) ; extra == 'full'
Requires-Dist: redis (==4.3.4) ; extra == 'full'
Requires-Dist: duckdb (==1.0.0) ; extra == 'full'
Requires-Dist: datetime (==4.3) ; extra == 'full'
Requires-Dist: pandas (==2.2.2) ; extra == 'full'
Provides-Extra: wshandler
Requires-Dist: python-engineio (==3.13.0) ; extra == 'wshandler'
Requires-Dist: python-socketio (==4.6.0) ; extra == 'wshandler'
Requires-Dist: aws-lambda-powertools (==1.25.5) ; extra == 'wshandler'
Requires-Dist: websockets (==13.0.1) ; extra == 'wshandler'
Requires-Dist: protobuf (==5.28.1) ; extra == 'wshandler'
Requires-Dist: pyzmq (==26.2.0) ; extra == 'wshandler'
Requires-Dist: redis (==4.3.4) ; extra == 'wshandler'
